MatrixBasedConvolution/__init__.py
MatrixBasedConvolution/mbc.py
MatrixBasedConvolution/utils.py
matrixbasedconvolution-0.1.0.dist-info/licenses/LICENSE
matrixbasedconvolution-0.1.0.dist-info/METADATA
matrixbasedconvolution-0.1.0.dist-info/WHEEL
matrixbasedconvolution-0.1.0.dist-info/top_level.txt
matrixbasedconvolution-0.1.0.dist-info/RECORD
